exec_python/__init__.py
exec_python/engine.py
exec_python/py.typed
exec_python/utils.py
exec_python-0.1.6.dist-info/METADATA
exec_python-0.1.6.dist-info/WHEEL
exec_python-0.1.6.dist-info/RECORD
