Metadata-Version: 2.4
Name: exec-python
Version: 0.1.6
Summary: Minimal engine to execute python code generated by LLMs, with a lot of customisation options.
Author-email: AtakanTekparmak <atakantekerparmak@gmail.com>
Requires-Python: >=3.10
Requires-Dist: pydantic>=2.8.0
